gapminder/__init__.py
gapminder/data.py
gapminder/gapminder.csv
gapminder/version.py
gapminder-0.1.dist-info/METADATA
gapminder-0.1.dist-info/RECORD
gapminder-0.1.dist-info/WHEEL
gapminder-0.1.dist-info/top_level.txt
