Metadata-Version: 2.1
Name: gapminder
Version: 0.1
Summary: A copy of R's gapminder teaching dataset.
Home-page: https://github.com/jstaf/gapminder
Author: Jeff Stafford
Author-email: jeff.stafford@queensu.ca
License: BSD3
Platform: UNKNOWN
Classifier: Programming Language :: Python :: 2.7
Classifier: Programming Language :: Python :: 3.4
Classifier: Programming Language :: Python :: 3.5
Classifier: Programming Language :: Python :: 3.6
Classifier: License :: OSI Approved :: BSD License
Classifier: Development Status :: 4 - Beta
